deepcomp/__init__.py
deepcomp/main.py
deepcomp/agent/__init__.py
deepcomp/agent/base.py
deepcomp/agent/brute_force.py
deepcomp/agent/dummy.py
deepcomp/agent/heuristics.py
deepcomp/env/__init__.py
deepcomp/env/entities/__init__.py
deepcomp/env/entities/map.py
deepcomp/env/entities/station.py
deepcomp/env/entities/user.py
deepcomp/env/multi_ue/__init__.py
deepcomp/env/multi_ue/central.py
deepcomp/env/multi_ue/multi_agent.py
deepcomp/env/single_ue/__init__.py
deepcomp/env/single_ue/base.py
deepcomp/env/single_ue/variants.py
deepcomp/env/util/__init__.py
deepcomp/env/util/movement.py
deepcomp/env/util/utility.py
deepcomp/util/__init__.py
deepcomp/util/callbacks.py
deepcomp/util/cli.py
deepcomp/util/constants.py
deepcomp/util/env_setup.py
deepcomp/util/logs.py
deepcomp/util/simulation.py
deepcomp-1.4.2.dist-info/LICENSE
deepcomp-1.4.2.dist-info/METADATA
deepcomp-1.4.2.dist-info/WHEEL
deepcomp-1.4.2.dist-info/entry_points.txt
deepcomp-1.4.2.dist-info/top_level.txt
deepcomp-1.4.2.dist-info/RECORD
